{
  "CEGI": "NONE",
  "DA": "NONE",
  "IGDHDFEAB": "CANCEL",
  "DHICEBBECGEBIGIB": "BUNT",
  "AHGGFEHCHAADBHI": "CANCEL",
  "CEFBEBHBH": "CANCEL",
  "BGDBIDAIA": "NONE",
  "IICDDBGGGDBEID": "BUNT",
  "DFDIEHEIE": "CANCEL",
  "DEIFB": "CANCEL",
  "AHGBIGHCBFBHEIHEB": "CANCEL",
  "BIAFAECE": "CANCEL",
  "EICH": "NONE",
  "ABHBBDC": "STEAL",
  "IB": "NONE",
  "GDABDDACAABEHCCEIBA": "BUNT",
  "D": "NONE",
  "GH": "NONE",
  "IHHDDAIG": "NONE",
  "CBEHGHDIGD": "BUNT",
  "BEEADC": "BUNT",
  "ABHC": "STEAL",
  "ABDBCEEIAGDC": "STEAL",
  "ABDGGHDIECC": "STEAL",
  "CIEBCGBE": "BUNT",
  "ABIHHBEIC": "STEAL",
  "ABAEGC": "STEAL",
  "E": "NONE",
  "CBHHHAAGFHIHEACC": "CANCEL",
  "ABHBCDIBGHHGC": "STEAL",
  "IHCAEGEBEHC": "BUNT",
  "AI": "NONE",
  "ABBHHEICIBBEDCHCBAGD": "BUNT",
  "BBBBAGEEA": "NONE",
  "ABDC": "STEAL",
  "ABGDHIAGC": "STEAL",
  "AEII": "NONE",
  "BGDBFHA": "CANCEL",
  "HBDACBDHBEGEABECDEH": "BUNT",
  "IIDDDHDIGBE": "BUNT",
  "FDAIB": "CANCEL",
  "ABGCIAC": "STEAL",
  "ABCDCBBEGEHC": "STEAL",
  "DIBAIDCHBEC": "BUNT",
  "CAEDBGEDADBEEIECCBG": "BUNT",
  "DGB": "NONE",
  "GAE": "NONE",
  "BHFBAHAAEHDDB": "CANCEL",
  "GIBBG": "NONE",
  "DB": "NONE",
  "FACA": "CANCEL",
  "ABBAECEGGCC": "STEAL",
  "IIAAEGCHFAEBC": "CANCEL",
  "": "NONE",
  "IBCIBEBHGEFGEHGDA": "CANCEL",
  "DGACAFBHECAGB": "CANCEL",
  "ABC": "STEAL",
  "BECIEIIDDEGD": "BUNT",
  "HHEDDI": "NONE",
  "ABEBC": "STEAL",
  "BADBBEA": "BUNT",
  "BIDAEGFIBDIBBAEAG": "CANCEL",
  "BCIEABC": "NONE",
  "A": "NONE",
  "DDEHHFHA": "CANCEL",
  "ABGCGGBAAC": "STEAL",
  "BIICHAGBABEGEBC": "BUNT",
  "DBEAICII": "BUNT",
  "I": "NONE",
  "DGDH": "NONE",
  "DECDDDIBBEAEHG": "BUNT",
  "ABECHC": "STEAL",
  "ABIBEGIC": "STEAL",
  "DEHAGB": "NONE",
  "AGBIB": "NONE",
  "ABCIC": "STEAL",
  "C": "NONE",
  "BEGHE": "BUNT",
  "DDAA": "NONE",
  "ABHDEC": "STEAL",
  "ABDHC": "STEAL",
  "ABDEIDHGHEGDC": "STEAL",
  "IGHIGGFA": "CANCEL",
  "DBDBFBHH": "CANCEL",
  "CDGAECBE": "BUNT",
  "CDIA": "NONE",
  "BG": "NONE",
  "ADABECD": "BUNT",
  "IAEGCH": "NONE",
  "ABIICEC": "STEAL",
  "BHIGDBCHHFDHGI": "CANCEL",
  "CHGCCEBEBIHACICEH": "BUNT",
  "BIBEBIGG": "BUNT",
  "BDGD": "NONE",
  "CDBFD": "CANCEL",
  "BEGAAEDBDH": "BUNT",
  "ADAIBEHHBGI": "BUNT",
  "HCHAFGAGHE": "CANCEL",
  "ADHEDGCDAAFDHABAC": "CANCEL",
  "HGHIGDABECGABIDIBEA": "BUNT"
}
